LICENSE
README.md
pyproject.toml
setup.py
DreamBoothFineTune.egg-info/PKG-INFO
DreamBoothFineTune.egg-info/SOURCES.txt
DreamBoothFineTune.egg-info/dependency_links.txt
DreamBoothFineTune.egg-info/requires.txt
DreamBoothFineTune.egg-info/top_level.txt
diffusion/Inpaint.py
diffusion/TextToImage.py
diffusion/__init__.py
utils/DreamBoothDataset.py
utils/PromptDataset.py
utils/__init__.py