Metadata-Version: 2.1
Name: DreamBoothFineTune
Version: 0.2.1
Home-page: https://github.com/skillfi/fine-tuning
Author: Alex
Requires-Python: >=3.8
License-File: LICENSE
Requires-Dist: pillow~=10.4.0
Requires-Dist: torchvision~=0.19.0
Requires-Dist: diffusers~=0.30.0
Requires-Dist: transformers~=4.44.0
Requires-Dist: tqdm~=4.66.4
Requires-Dist: datasets~=2.20.0
Requires-Dist: bitsandbytes
Provides-Extra: cuda
Requires-Dist: torch==2.4.0+cu124; extra == "cuda"
Requires-Dist: torchvision==0.19.0+cu124; extra == "cuda"
Requires-Dist: torchaudio==2.4.0+cu124; extra == "cuda"
